PadimAD.py
__init__.py
anomaly_detection_ui.py
main.py
ai/DTO.py
ai/__init__.py
ai/feature_extraction.py
config/DTO.py
config/__init__.py
constants/__init__.py
constants/constants_ai.py
data/__init__.py
data/dataset.py
data/transform.py
gui/__init__.py
gui/main_frame.py
gui/gui_components/__init__.py
gui/gui_components/train_parameters_widget.py
gui/gui_enums/__init__.py
gui/gui_enums/ad_status.py
vision/__init__.py
vision/rendering.py
padim_ad-0.0.1.dist-info/LICENSE.txt
padim_ad-0.0.1.dist-info/METADATA
padim_ad-0.0.1.dist-info/WHEEL
padim_ad-0.0.1.dist-info/top_level.txt
padim_ad-0.0.1.dist-info/RECORD
