Metadata-Version: 2.2
Name: padim_ad
Version: 0.0.1
Summary: Padim Anomaly Detection package
Author-email: Stephan Pirner <stephan.pirner93@gmail.com>
Project-URL: Homepage, https://github.com/pypa/sampleproject
Project-URL: Issues, https://github.com/pypa/sampleproject/issues
Classifier: Programming Language :: Python :: 3
Classifier: Operating System :: OS Independent
Requires-Python: >=3.9
License-File: LICENSE.txt
